02_ALU/alu.v
`timescale 1ns/1ns
module alu (
    input clk, rst,
    input [7:0] a, b,
    input [4:0] op,
    output[7:0] res,
    output reg z, c, o, n, p
);
 parameter add = 5'd0, sub = 5'd1, inc = 5'd2, dec = 5'd3, neg = 5'd4,
           AND = 5'd5, OR = 5'd6, XOR = 5'd7, NOT = 5'd8, 
           LSL = 5'd9, LSR = 5'd10, ASL = 5'd11, ASR = 5'd12, 
           RL = 5'd13, RR = 5'd14, RLC = 5'd15, RRC = 5'd16,
           equal = 5'd17, GT = 5'd18, LT = 5'd19;
reg carry, overflow, c_reg;
reg [7:0] result;        
 always @(*) begin
    {carry, overflow, result} = 10'd0;
    case (op)
       add  : begin                                       
             {carry,result} = a + b;
              overflow = (a[7]==b[7]) & (result[7]!=a[7]);
        end
        sub  : begin                                       
             {carry,result} = a - b;
              overflow = (a[7]!=b[7]) & (result[7]!=a[7]);
                   end
       inc : {carry, result} = a + 8'd1;
       dec : {carry, result} = a - 8'd1;
       neg :  result = (~a) + 8'd1;
       AND :  result = a & b;
       OR :   result = a | b;
       XOR :  result = a ^ b;
       NOT :  result = ~a;
       LSL :  {carry, result} = {a, 1'b0};
       LSR :  {result, carry} = {1'b0, a};
       ASL :  {carry, result} = {a, 1'b0};
       ASR :  {result, carry} = {a[7], a};
       RL :    result = {a[6:0], a[7]};
       RR :    result = {a[0], a[7:1]};
       RLC :  {carry, result} = {a, c_reg};
       RRC :  {result, carry} = {c_reg, a};
       equal : result = {7'd0, (a == b)};
       GT :    result = {7'd0, (a > b)};
       LT :    result = {7'd0, (a < b)};
        default: result = 8'd0;
    endcase
 end
 always @(posedge clk or posedge rst) begin
    if (rst) {z, c, o, n, p} <= 5'd0;
    else {z, c, o, n, p, c_reg} <= {(result == 8'd0), carry, overflow, result[7], (~^result), carry};
 end
 assign res = result;
endmodule

02_ALU/alu_tb.v
`timescale 1ns/1ns
// ================================================================
//  Self-checking testbench for alu.v
//
//  Sampling strategy (critical for RLC/RRC):
//    res  = combinational → sampled BEFORE posedge (after 2ns settle)
//    z,c,o,n,p = registered → sampled AFTER posedge (+1ns)
//
//  Coverage: all 20 opcodes, carry/overflow corners, signed overflow,
//            RLC/RRC c_reg feedback, reset, mid-op reset, default op.
// ================================================================
module alu_tb;

    // ---- DUT signals -------------------------------------------
    reg        clk, rst;
    reg  [7:0] a, b;
    reg  [4:0] op;
    wire [7:0] res;
    wire       z, c, o, n, p;

    // ---- DUT instance ------------------------------------------
    alu dut (
        .clk(clk), .rst(rst),
        .a(a), .b(b), .op(op),
        .res(res),
        .z(z), .c(c), .o(o), .n(n), .p(p)
    );

    // ---- Clock: 10 ns period -----------------------------------
    initial clk = 0;
    always #5 clk = ~clk;

    // ---- Opcode aliases ----------------------------------------
    localparam
        OP_ADD=5'd0,  OP_SUB=5'd1,  OP_INC=5'd2,  OP_DEC=5'd3,
        OP_NEG=5'd4,  OP_AND=5'd5,  OP_OR =5'd6,  OP_XOR=5'd7,
        OP_NOT=5'd8,  OP_LSL=5'd9,  OP_LSR=5'd10, OP_ASL=5'd11,
        OP_ASR=5'd12, OP_RL =5'd13, OP_RR =5'd14, OP_RLC=5'd15,
        OP_RRC=5'd16, OP_EQ =5'd17, OP_GT =5'd18, OP_LT =5'd19;

    // ---- Scoreboard --------------------------------------------
    integer pass_cnt = 0;
    integer fail_cnt = 0;
    integer test_num = 0;

    // ---- Parity helper (even parity = 1 when even number of 1s)
    function automatic PAR;
        input [7:0] v;
        PAR = ~^v;
    endfunction

    // ================================================================
    //  CHECK_ALL task
    //    Call with inputs already applied.
    //    Samples res before posedge, flags after posedge.
    // ================================================================
    task CHECK_ALL;
        input [7:0]   exp_res;
        input         exp_z, exp_c, exp_o, exp_n, exp_p;
        input [127:0] label;
        reg   [7:0]   got_res;
        reg           got_z, got_c, got_o, got_n, got_p;
        integer       ok;
    begin
        // 1) Let combinational settle, then snapshot res
        #2;
        got_res = res;

        // 2) Wait for posedge, then snapshot registered flags
        @(posedge clk); #1;
        got_z = z; got_c = c; got_o = o; got_n = n; got_p = p;

        test_num = test_num + 1;
        ok = (got_res === exp_res) && (got_z === exp_z) &&
             (got_c === exp_c)     && (got_o === exp_o) &&
             (got_n === exp_n)     && (got_p === exp_p);

        if (ok) begin
            $display("PASS [T%0d] %s", test_num, label);
            pass_cnt = pass_cnt + 1;
        end else begin
            $display("FAIL [T%0d] %s", test_num, label);
            $display("       a=%02h  b=%02h  op=%0d", a, b, op);
            if (got_res !== exp_res)
                $display("       res: exp=%02h  got=%02h  <--", exp_res, got_res);
            if (got_z   !== exp_z)
                $display("       Z  : exp=%0b   got=%0b   <--", exp_z, got_z);
            if (got_c   !== exp_c)
                $display("       C  : exp=%0b   got=%0b   <--", exp_c, got_c);
            if (got_o   !== exp_o)
                $display("       OVF: exp=%0b   got=%0b   <--", exp_o, got_o);
            if (got_n   !== exp_n)
                $display("       N  : exp=%0b   got=%0b   <--", exp_n, got_n);
            if (got_p   !== exp_p)
                $display("       P  : exp=%0b   got=%0b   <--", exp_p, got_p);
            fail_cnt = fail_cnt + 1;
        end
    end
    endtask

    // ================================================================
    //  APPLY + CHECK  (combined convenience task)
    // ================================================================
    task APPLY;
        input [7:0]   _a, _b;
        input [4:0]   _op;
        input [7:0]   exp_res;
        input         exp_z, exp_c, exp_o, exp_n, exp_p;
        input [127:0] label;
    begin
        a = _a; b = _b; op = _op;
        CHECK_ALL(exp_res, exp_z, exp_c, exp_o, exp_n, exp_p, label);
    end
    endtask

    // ================================================================
    //  MAIN STIMULUS
    // ================================================================
    initial begin
        $dumpfile("alu_tb.vcd");
        $dumpvars(0, alu_tb);

        // ---- Reset check ----------------------------------------
        rst = 1; a = 0; b = 0; op = 0;
        @(posedge clk); #1;
        test_num = test_num + 1;
        if ({z,c,o,n,p} !== 5'b00000) begin
            $display("FAIL [T%0d] RESET: flags not cleared", test_num);
            fail_cnt = fail_cnt + 1;
        end else begin
            $display("PASS [T%0d] RESET: all flags cleared", test_num);
            pass_cnt = pass_cnt + 1;
        end
        rst = 0;

        // ===========================================================
        // ADD
        // ===========================================================
        // Basic positive sum
        APPLY(8'h03, 8'h04, OP_ADD, 8'h07,
              0,0,0,0,PAR(8'h07), "ADD  3+4=7");

        // Unsigned carry: 0xFF+0x01=0x00 (carry=1, no signed overflow)
        APPLY(8'hFF, 8'h01, OP_ADD, 8'h00,
              1,1,0,0,PAR(8'h00), "ADD  FF+01 carry wrap");

        // Signed overflow: 0x7F+0x01=0x80 (pos+pos=neg)
        APPLY(8'h7F, 8'h01, OP_ADD, 8'h80,
              0,0,1,1,PAR(8'h80), "ADD  7F+01 signed OVF");

        // Zero sum
        APPLY(8'h00, 8'h00, OP_ADD, 8'h00,
              1,0,0,0,PAR(8'h00), "ADD  0+0=0 zero flag");

        // -128 + -128 = -256: wraps to 0x00, carry=1, SIGNED OVERFLOW (neg+neg=pos)
        APPLY(8'h80, 8'h80, OP_ADD, 8'h00,
              1,1,1,0,PAR(8'h00), "ADD  80+80 signed OVF+carry");

        // Signed overflow: neg+neg=pos 0x80+0xFF=0x7F
        APPLY(8'h80, 8'hFF, OP_ADD, 8'h7F,
              0,1,1,0,PAR(8'h7F), "ADD  80+FF signed OVF neg+neg=pos");

        // ===========================================================
        // SUB
        // ===========================================================
        APPLY(8'h05, 8'h03, OP_SUB, 8'h02,
              0,0,0,0,PAR(8'h02), "SUB  5-3=2");

        // Borrow: 0-1=0xFF, carry=1
        APPLY(8'h00, 8'h01, OP_SUB, 8'hFF,
              0,1,0,1,PAR(8'hFF), "SUB  0-1 borrow");

        // Signed overflow: 0x80-0x01=0x7F (neg-pos=pos)
        APPLY(8'h80, 8'h01, OP_SUB, 8'h7F,
              0,0,1,0,PAR(8'h7F), "SUB  80-01 signed OVF");

        // Equal operands → zero
        APPLY(8'hAA, 8'hAA, OP_SUB, 8'h00,
              1,0,0,0,PAR(8'h00), "SUB  AA-AA=0");

        // ===========================================================
        // INC
        // ===========================================================
        APPLY(8'h0A, 8'hXX, OP_INC, 8'h0B,
              0,0,0,0,PAR(8'h0B), "INC  0A->0B");

        APPLY(8'hFF, 8'hXX, OP_INC, 8'h00,
              1,1,0,0,PAR(8'h00), "INC  FF->00 carry");

        // ===========================================================
        // DEC
        // ===========================================================
        APPLY(8'h05, 8'hXX, OP_DEC, 8'h04,
              0,0,0,0,PAR(8'h04), "DEC  05->04");

        APPLY(8'h00, 8'hXX, OP_DEC, 8'hFF,
              0,1,0,1,PAR(8'hFF), "DEC  00->FF carry");

        APPLY(8'h01, 8'hXX, OP_DEC, 8'h00,
              1,0,0,0,PAR(8'h00), "DEC  01->00 zero");

        // ===========================================================
        // NEG  (~a + 1)
        // ===========================================================
        APPLY(8'h05, 8'hXX, OP_NEG, 8'hFB,
              0,0,0,1,PAR(8'hFB), "NEG  05->FB");

        APPLY(8'h00, 8'hXX, OP_NEG, 8'h00,
              1,0,0,0,PAR(8'h00), "NEG  00->00 zero");

        APPLY(8'hFF, 8'hXX, OP_NEG, 8'h01,
              0,0,0,0,PAR(8'h01), "NEG  FF->01");

        // ===========================================================
        // AND
        // ===========================================================
        APPLY(8'hF0, 8'h0F, OP_AND, 8'h00,
              1,0,0,0,PAR(8'h00), "AND  F0&0F=00");

        APPLY(8'hAA, 8'hFF, OP_AND, 8'hAA,
              0,0,0,1,PAR(8'hAA), "AND  AA&FF=AA");

        APPLY(8'hFF, 8'hFF, OP_AND, 8'hFF,
              0,0,0,1,PAR(8'hFF), "AND  FF&FF=FF");

        // ===========================================================
        // OR
        // ===========================================================
        APPLY(8'hA0, 8'h0B, OP_OR, 8'hAB,
              0,0,0,1,PAR(8'hAB), "OR   A0|0B=AB");

        APPLY(8'h00, 8'h00, OP_OR, 8'h00,
              1,0,0,0,PAR(8'h00), "OR   00|00=00");

        // ===========================================================
        // XOR
        // ===========================================================
        APPLY(8'hFF, 8'hFF, OP_XOR, 8'h00,
              1,0,0,0,PAR(8'h00), "XOR  FF^FF=00");

        APPLY(8'hA5, 8'h5A, OP_XOR, 8'hFF,
              0,0,0,1,PAR(8'hFF), "XOR  A5^5A=FF");

        APPLY(8'h00, 8'hFF, OP_XOR, 8'hFF,
              0,0,0,1,PAR(8'hFF), "XOR  00^FF=FF");

        // ===========================================================
        // NOT
        // ===========================================================
        APPLY(8'h00, 8'hXX, OP_NOT, 8'hFF,
              0,0,0,1,PAR(8'hFF), "NOT  00->FF");

        APPLY(8'hFF, 8'hXX, OP_NOT, 8'h00,
              1,0,0,0,PAR(8'h00), "NOT  FF->00");

        APPLY(8'hA5, 8'hXX, OP_NOT, 8'h5A,
              0,0,0,0,PAR(8'h5A), "NOT  A5->5A");

        // ===========================================================
        // LSL  {carry,result}={a,1'b0}
        // ===========================================================
        APPLY(8'hA5, 8'hXX, OP_LSL, 8'h4A,
              0,1,0,0,PAR(8'h4A), "LSL  A5->4A c=1");

        APPLY(8'h01, 8'hXX, OP_LSL, 8'h02,
              0,0,0,0,PAR(8'h02), "LSL  01->02");

        APPLY(8'h80, 8'hXX, OP_LSL, 8'h00,
              1,1,0,0,PAR(8'h00), "LSL  80->00 carry+zero");

        // ===========================================================
        // LSR  {result,carry}={1'b0,a}
        // ===========================================================
        APPLY(8'hA5, 8'hXX, OP_LSR, 8'h52,
              0,1,0,0,PAR(8'h52), "LSR  A5->52 c=1");

        APPLY(8'h80, 8'hXX, OP_LSR, 8'h40,
              0,0,0,0,PAR(8'h40), "LSR  80->40");

        APPLY(8'h01, 8'hXX, OP_LSR, 8'h00,
              1,1,0,0,PAR(8'h00), "LSR  01->00 carry+zero");

        // ===========================================================
        // ASL  (same encoding as LSL)
        // ===========================================================
        APPLY(8'hC0, 8'hXX, OP_ASL, 8'h80,
              0,1,0,1,PAR(8'h80), "ASL  C0->80 c=1");

        APPLY(8'h01, 8'hXX, OP_ASL, 8'h02,
              0,0,0,0,PAR(8'h02), "ASL  01->02");

        // ===========================================================
        // ASR  {result,carry}={a[7],a}  (sign-extend right shift)
        // ===========================================================
        // Negative number: 0x80 → 0xC0, carry=0
        APPLY(8'h80, 8'hXX, OP_ASR, 8'hC0,
              0,0,0,1,PAR(8'hC0), "ASR  80->C0 sign ext");

        // Positive odd: 0x55 → 0x2A, carry=1
        APPLY(8'h55, 8'hXX, OP_ASR, 8'h2A,
              0,1,0,0,PAR(8'h2A), "ASR  55->2A c=1");

        // 0xFF → 0xFF, carry=1
        APPLY(8'hFF, 8'hXX, OP_ASR, 8'hFF,
              0,1,0,1,PAR(8'hFF), "ASR  FF->FF c=1");

        // ===========================================================
        // RL  {a[6:0], a[7]}
        // ===========================================================
        APPLY(8'hA5, 8'hXX, OP_RL, 8'h4B,
              0,0,0,0,PAR(8'h4B), "RL   A5->4B");

        APPLY(8'h80, 8'hXX, OP_RL, 8'h01,
              0,0,0,0,PAR(8'h01), "RL   80->01");

        APPLY(8'h01, 8'hXX, OP_RL, 8'h02,
              0,0,0,0,PAR(8'h02), "RL   01->02");

        // ===========================================================
        // RR  {a[0], a[7:1]}
        // ===========================================================
        APPLY(8'hA5, 8'hXX, OP_RR, 8'hD2,
              0,0,0,1,PAR(8'hD2), "RR   A5->D2");

        APPLY(8'h01, 8'hXX, OP_RR, 8'h80,
              0,0,0,1,PAR(8'h80), "RR   01->80");

        APPLY(8'hFE, 8'hXX, OP_RR, 8'h7F,
              0,0,0,0,PAR(8'h7F), "RR   FE->7F");

        // ===========================================================
        // RLC  {carry,result}={a, c_reg}
        //   c_reg is latched carry from previous clock.
        //   Strategy: use ADD FF+01 to set carry=1, then run RLC.
        //   Must check res BEFORE posedge (combinational) and flags AFTER.
        // ===========================================================

        // --- Setup: produce carry=1 ---
        APPLY(8'hFF, 8'h01, OP_ADD, 8'h00,
              1,1,0,0,PAR(8'h00), "RLC_SETUP  ADD FF+01 c->1");

        // RLC A5 with c_reg=1: {carry,result}={A5,1}=1_0100_1011 → res=4B, c=1
        APPLY(8'hA5, 8'hXX, OP_RLC, 8'h4B,
              0,1,0,0,PAR(8'h4B), "RLC  A5,c_reg=1 -> 4B c=1");

        // c_reg still 1 (carry from previous RLC=1), same result
        APPLY(8'hA5, 8'hXX, OP_RLC, 8'h4B,
              0,1,0,0,PAR(8'h4B), "RLC  A5,c_reg=1 again -> 4B");

        // --- Clear carry via AND 0,0 ---
        APPLY(8'h00, 8'h00, OP_AND, 8'h00,
              1,0,0,0,PAR(8'h00), "RLC_SETUP  AND 00&00 c->0");

        // RLC A5 with c_reg=0: {carry,result}={A5,0}=1_0100_1010 → res=4A, c=1
        APPLY(8'hA5, 8'hXX, OP_RLC, 8'h4A,
              0,1,0,0,PAR(8'h4A), "RLC  A5,c_reg=0 -> 4A c=1");

        // RLC with zero data: 0x00, c_reg=1 → res=01, c=0
        APPLY(8'h00, 8'hXX, OP_RLC, 8'h01,
              0,0,0,0,PAR(8'h01), "RLC  00,c_reg=1 -> 01 c=0");

        // ===========================================================
        // RRC  {result,carry}={c_reg,a}
        //   c_reg=0 after the previous RLC (RLC 00 → carry=0)
        // ===========================================================
        // c_reg=0, a=A5=1010_0101 → {result,carry}={0,1010_0101} → res=0101_0010=52, c=1
        APPLY(8'hA5, 8'hXX, OP_RRC, 8'h52,
              0,1,0,0,PAR(8'h52), "RRC  A5,c_reg=0 -> 52 c=1");

        // c_reg=1 now, a=A5 → {result,carry}={1,1010_0101} → res=1101_0010=D2, c=1
        APPLY(8'hA5, 8'hXX, OP_RRC, 8'hD2,
              0,1,0,1,PAR(8'hD2), "RRC  A5,c_reg=1 -> D2 c=1");

        // c_reg=1, a=00 → {result,carry}={1,0000_0000}→ res=1000_0000=80, c=0
        APPLY(8'h00, 8'hXX, OP_RRC, 8'h80,
              0,0,0,1,PAR(8'h80), "RRC  00,c_reg=1 -> 80 c=0");

        // ===========================================================
        // EQUAL
        // ===========================================================
        APPLY(8'h07, 8'h07, OP_EQ, 8'h01,
              0,0,0,0,PAR(8'h01), "EQ   07==07 -> 1");

        APPLY(8'h07, 8'h08, OP_EQ, 8'h00,
              1,0,0,0,PAR(8'h00), "EQ   07!=08 -> 0");

        APPLY(8'h00, 8'h00, OP_EQ, 8'h01,
              0,0,0,0,PAR(8'h01), "EQ   00==00 -> 1");

        // ===========================================================
        // GT  (unsigned)
        // ===========================================================
        APPLY(8'hFF, 8'h00, OP_GT, 8'h01,
              0,0,0,0,PAR(8'h01), "GT   FF>00 -> 1");

        APPLY(8'h00, 8'hFF, OP_GT, 8'h00,
              1,0,0,0,PAR(8'h00), "GT   00>FF -> 0");

        APPLY(8'h05, 8'h05, OP_GT, 8'h00,
              1,0,0,0,PAR(8'h00), "GT   05==05 -> 0");

        // ===========================================================
        // LT  (unsigned)
        // ===========================================================
        APPLY(8'h00, 8'hFF, OP_LT, 8'h01,
              0,0,0,0,PAR(8'h01), "LT   00<FF -> 1");

        APPLY(8'hFF, 8'h00, OP_LT, 8'h00,
              1,0,0,0,PAR(8'h00), "LT   FF<00 -> 0");

        APPLY(8'h05, 8'h05, OP_LT, 8'h00,
              1,0,0,0,PAR(8'h00), "LT   05==05 -> 0");

        // ===========================================================
        // DEFAULT opcode (unused code → res=0)
        // ===========================================================
        a = 8'hAA; b = 8'h55; op = 5'd20;
        #2;
        test_num = test_num + 1;
        if (res !== 8'h00) begin
            $display("FAIL [T%0d] DEFAULT op=20 res=%02h (exp=00)", test_num, res);
            fail_cnt = fail_cnt + 1;
        end else begin
            $display("PASS [T%0d] DEFAULT op=20 res=00", test_num);
            pass_cnt = pass_cnt + 1;
        end
        @(posedge clk); #1; // consume clock

        // ===========================================================
        // MID-OPERATION RESET
        // ===========================================================
        a = 8'hFF; b = 8'hFF; op = OP_ADD;
        #2; rst = 1;
        @(posedge clk); #1;
        test_num = test_num + 1;
        if ({z,c,o,n,p} !== 5'b00000) begin
            $display("FAIL [T%0d] MID-OP RESET: flags=%b%b%b%b%b (exp=00000)",
                     test_num, z, c, o, n, p);
            fail_cnt = fail_cnt + 1;
        end else begin
            $display("PASS [T%0d] MID-OP RESET: all flags cleared", test_num);
            pass_cnt = pass_cnt + 1;
        end
        rst = 0;

        // ===========================================================
        // SUMMARY
        // ===========================================================
        $display("\n==============================================");
        $display("  RESULTS: %0d passed,  %0d failed  /  %0d total",
                 pass_cnt, fail_cnt, test_num);
        if (fail_cnt == 0)
            $display("  *** ALL TESTS PASSED ***");
        else
            $display("  *** %0d TEST(S) FAILED — see above ***", fail_cnt);
        $display("==============================================\n");

        $finish;
    end

endmodule

02_ALU/alu_tb.vcd
$date
	Tue Jun 16 03:28:24 2026
$end
$version
	Icarus Verilog
$end
$timescale
	1ns
$end
$scope module alu_tb $end
$var wire 1 ! z $end
$var wire 8 " res [7:0] $end
$var wire 1 # p $end
$var wire 1 $ o $end
$var wire 1 % n $end
$var wire 1 & c $end
$var parameter 5 ' OP_ADD $end
$var parameter 5 ( OP_AND $end
$var parameter 5 ) OP_ASL $end
$var parameter 5 * OP_ASR $end
$var parameter 5 + OP_DEC $end
$var parameter 5 , OP_EQ $end
$var parameter 5 - OP_GT $end
$var parameter 5 . OP_INC $end
$var parameter 5 / OP_LSL $end
$var parameter 5 0 OP_LSR $end
$var parameter 5 1 OP_LT $end
$var parameter 5 2 OP_NEG $end
$var parameter 5 3 OP_NOT $end
$var parameter 5 4 OP_OR $end
$var parameter 5 5 OP_RL $end
$var parameter 5 6 OP_RLC $end
$var parameter 5 7 OP_RR $end
$var parameter 5 8 OP_RRC $end
$var parameter 5 9 OP_SUB $end
$var parameter 5 : OP_XOR $end
$var reg 8 ; a [7:0] $end
$var reg 8 < b [7:0] $end
$var reg 1 = clk $end
$var reg 5 > op [4:0] $end
$var reg 1 ? rst $end
$var integer 32 @ fail_cnt [31:0] $end
$var integer 32 A pass_cnt [31:0] $end
$var integer 32 B test_num [31:0] $end
$scope function PAR $end
$upscope $end
$scope module dut $end
$var wire 8 C a [7:0] $end
$var wire 8 D b [7:0] $end
$var wire 1 = clk $end
$var wire 5 E op [4:0] $end
$var wire 8 F res [7:0] $end
$var wire 1 ? rst $end
$var parameter 5 G AND $end
$var parameter 5 H ASL $end
$var parameter 5 I ASR $end
$var parameter 5 J GT $end
$var parameter 5 K LSL $end
$var parameter 5 L LSR $end
$var parameter 5 M LT $end
$var parameter 5 N NOT $end
$var parameter 5 O OR $end
$var parameter 5 P RL $end
$var parameter 5 Q RLC $end
$var parameter 5 R RR $end
$var parameter 5 S RRC $end
$var parameter 5 T XOR $end
$var parameter 5 U add $end
$var parameter 5 V dec $end
$var parameter 5 W equal $end
$var parameter 5 X inc $end
$var parameter 5 Y neg $end
$var parameter 5 Z sub $end
$var reg 1 & c $end
$var reg 1 [ c_reg $end
$var reg 1 \ carry $end
$var reg 1 % n $end
$var reg 1 $ o $end
$var reg 1 ] overflow $end
$var reg 1 # p $end
$var reg 8 ^ result [7:0] $end
$var reg 1 ! z $end
$upscope $end
$scope task APPLY $end
$var reg 8 _ _a [7:0] $end
$var reg 8 ` _b [7:0] $end
$var reg 5 a _op [4:0] $end
$var reg 1 b exp_c $end
$var reg 1 c exp_n $end
$var reg 1 d exp_o $end
$var reg 1 e exp_p $end
$var reg 8 f exp_res [7:0] $end
$var reg 1 g exp_z $end
$var reg 128 h label [127:0] $end
$upscope $end
$scope task CHECK_ALL $end
$var reg 1 i exp_c $end
$var reg 1 j exp_n $end
$var reg 1 k exp_o $end
$var reg 1 l exp_p $end
$var reg 8 m exp_res [7:0] $end
$var reg 1 n exp_z $end
$var reg 1 o got_c $end
$var reg 1 p got_n $end
$var reg 1 q got_o $end
$var reg 1 r got_p $end
$var reg 8 s got_res [7:0] $end
$var reg 1 t got_z $end
$var reg 128 u label [127:0] $end
$var integer 32 v ok [31:0] $end
$upscope $end
$upscope $end
$enddefinitions $end
$comment Show the parameter values. $end
$dumpall
b1 Z
b100 Y
b10 X
b10001 W
b11 V
b0 U
b111 T
b10000 S
b1110 R
b1111 Q
b1101 P
b110 O
b1000 N
b10011 M
b1010 L
b1001 K
b10010 J
b1100 I
b1011 H
b101 G
b111 :
b1 9
b10000 8
b1110 7
b1111 6
b1101 5
b110 4
b1000 3
b100 2
b10011 1
b1010 0
b1001 /
b10 .
b10010 -
b10001 ,
b11 +
b1100 *
b1011 )
b101 (
b0 '
$end
#0
$dumpvars
bx v
bx u
xt
bx s
xr
xq
xp
xo
xn
bx m
xl
xk
xj
xi
bx h
xg
bx f
xe
xd
xc
xb
bx a
bx `
bx _
b0 ^
0]
0\
x[
b0 F
b0 E
b0 D
b0 C
b0 B
b0 A
b0 @
1?
b0 >
0=
b0 <
b0 ;
0&
0%
0$
0#
b0 "
0!
$end
#5
1=
#6
b111 "
b111 F
b111 ^
b1000001010001000100010000100000001000000011001100101011001101000011110100110111 u
0l
0j
0k
0i
0n
b111 m
b100 <
b100 D
b11 ;
b11 C
b1000001010001000100010000100000001000000011001100101011001101000011110100110111 h
0e
0c
0d
0b
0g
b111 f
b0 a
b100 `
b11 _
0?
b1 A
b1 B
#8
b111 s
#10
0=
#15
b111 "
b111 F
b111 ^
0[
1=
#16
1\
b0 "
b0 F
b0 ^
b1000110010001100010101100110000001100010010000001100011011000010111001001110010011110010010000001110111011100100110000101110000 u
1l
1i
1n
b0 m
b1 <
b1 D
b11111111 ;
b11111111 C
b1000110010001100010101100110000001100010010000001100011011000010111001001110010011110010010000001110111011100100110000101110000 h
1e
1b
1g
b0 f
b1 `
b11111111 _
b10 A
b1 v
b10 B
0r
0p
0q
0o
0t
#18
b0 s
#20
0=
#25
1\
1!
1&
1#
1[
1=
#26
1]
b10000000 "
b10000000 F
b10000000 ^
0\
b110111010001100010101100110000001100010010000001110011011010010110011101101110011001010110010000100000010011110101011001000110 u
0l
1j
1k
0i
0n
b10000000 m
b1111111 ;
b1111111 C
b110111010001100010101100110000001100010010000001110011011010010110011101101110011001010110010000100000010011110101011001000110 h
0e
1c
1d
0b
0g
b10000000 f
b1111111 _
b11 A
b11 B
1r
1o
1t
#28
b10000000 s
#30
0=
#35
1]
b10000000 "
b10000000 F
b10000000 ^
0!
0&
1$
1%
0#
0[
1=
#36
0]
b0 "
b0 F
b0 ^
b100000001100000010101100110000001111010011000000100000011110100110010101110010011011110010000001100110011011000110000101100111 u
1l
0j
0k
1n
b0 m
b0 <
b0 D
b0 ;
b0 C
b100000001100000010101100110000001111010011000000100000011110100110010101110010011011110010000001100110011011000110000101100111 h
1e
0c
0d
1g
b0 f
b0 `
b0 _
b100 A
b100 B
0r
1p
1q
0o
0t
#38
b0 s
#40
0=
#45
1!
0$
0%
1#
1=
#46
1]
1\
b1110011011010010110011101101110011001010110010000100000010011110101011001000110001010110110001101100001011100100111001001111001 u
1k
1i
b10000000 <
b10000000 D
b10000000 ;
b10000000 C
b1110011011010010110011101101110011001010110010000100000010011110101011001000110001010110110001101100001011100100111001001111001 h
1d
1b
b10000000 `
b10000000 _
b101 A
b101 B
1r
0p
0q
1t
#50
0=
#55
1\
1]
1&
1$
1[
1=
#56
b1111111 "
b1111111 F
b1111111 ^
1\
1]
b100000010011110101011001000110001000000110111001100101011001110010101101101110011001010110011100111101011100000110111101110011 u
0l
0n
b1111111 m
b11111111 <
b11111111 D
b100000010011110101011001000110001000000110111001100101011001110010101101101110011001010110011100111101011100000110111101110011 h
0e
0g
b1111111 f
b11111111 `
b110 A
b110 B
1q
1o
#58
b1111111 s
#60
0=
#65
0!
0#
1=
#66
0\
0]
b10 "
b10 F
b10 ^
b1010011010101010100001000100000001000000011010100101101001100110011110100110010 u
0k
0i
b10 m
b1 >
b1 E
b11 <
b11 D
b101 ;
b101 C
b1010011010101010100001000100000001000000011010100101101001100110011110100110010 h
0d
0b
b10 f
b1 a
b11 `
b101 _
b111 A
b111 B
0r
0t
#68
b10 s
#70
0=
#75
b10 "
b10 F
b10 ^
0&
0$
0[
1=
#76
1\
b11111111 "
b11111111 F
b11111111 ^
b10100110101010101000010001000000010000000110000001011010011000100100000011000100110111101110010011100100110111101110111 u
1l
1j
1i
b11111111 m
b1 <
b1 D
b0 ;
b0 C
b10100110101010101000010001000000010000000110000001011010011000100100000011000100110111101110010011100100110111101110111 h
1e
1c
1b
b11111111 f
b1 `
b0 _
b1000 A
b1000 B
0q
0o
#78
b11111111 s
#80
0=
#85
1\
b11111111 "
b11111111 F
b11111111 ^
1&
1%
1#
1[
1=
#86
1]
0\
b1111111 "
b1111111 F
b1111111 ^
b111000001100000010110100110000001100010010000001110011011010010110011101101110011001010110010000100000010011110101011001000110 u
0l
0j
1k
0i
b1111111 m
b10000000 ;
b10000000 C
b111000001100000010110100110000001100010010000001110011011010010110011101101110011001010110010000100000010011110101011001000110 h
0e
0c
1d
0b
b1111111 f
b10000000 _
b1001 A
b1001 B
1r
1p
1o
#88
b1111111 s
#90
0=
#95
1]
b1111111 "
b1111111 F
b1111111 ^
0&
1$
0%
0#
0[
1=
#96
0]
b0 "
b0 F
b0 ^
b10100110101010101000010001000000010000001000001010000010010110101000001010000010011110100110000 u
1l
0k
1n
b0 m
b10101010 <
b10101010 D
b10101010 ;
b10101010 C
b10100110101010101000010001000000010000001000001010000010010110101000001010000010011110100110000 h
1e
0d
1g
b0 f
b10101010 `
b10101010 _
b1010 A
b1010 B
0r
0p
1q
0o
#98
b0 s
#100
0=
#105
1!
0$
1#
1=
#106
b1011 "
b1011 F
b1011 ^
b100100101001110010000110010000000100000001100000100000100101101001111100011000001000010 u
0l
0n
b1011 m
b10 >
b10 E
bx <
bx D
b1010 ;
b1010 C
b100100101001110010000110010000000100000001100000100000100101101001111100011000001000010 h
0e
0g
b1011 f
b10 a
bx `
b1010 _
b1011 A
b1011 B
1r
0q
1t
#108
b1011 s
#110
0=
#115
0!
0#
1=
#116
1\
b0 "
b0 F
b0 ^
b1001110010000110010000000100000010001100100011000101101001111100011000000110000001000000110001101100001011100100111001001111001 u
1l
1i
1n
b0 m
b11111111 ;
b11111111 C
b1001110010000110010000000100000010001100100011000101101001111100011000000110000001000000110001101100001011100100111001001111001 h
1e
1b
1g
b0 f
b11111111 _
b1100 A
b1100 B
0r
0t
#118
b0 s
#120
0=
#125
1\
1!
1&
1#
1[
1=
#126
b100 "
b100 F
b100 ^
0\
b100010001000101010000110010000000100000001100000011010100101101001111100011000000110100 u
0l
0i
0n
b100 m
b11 >
b11 E
b101 ;
b101 C
b100010001000101010000110010000000100000001100000011010100101101001111100011000000110100 h
0e
0b
0g
b100 f
b11 a
b101 _
b1101 A
b1101 B
1r
1o
1t
#128
b100 s
#130
0=
#135
b100 "
b100 F
b100 ^
0!
0&
0#
0[
1=
#136
1\
b11111111 "
b11111111 F
b11111111 ^
b1000101010000110010000000100000001100000011000000101101001111100100011001000110001000000110001101100001011100100111001001111001 u
1l
1j
1i
b11111111 m
b0 ;
b0 C
b1000101010000110010000000100000001100000011000000101101001111100100011001000110001000000110001101100001011100100111001001111001 h
1e
1c
1b
b11111111 f
b0 _
b1110 A
b1110 B
0r
0o
0t
#138
b11111111 s
#140
0=
#145
1\
b11111111 "
b11111111 F
b11111111 ^
1&
1%
1#
1[
1=
#146
0\
b0 "
b0 F
b0 ^
b1000100010001010100001100100000001000000011000000110001001011010011111000110000001100000010000001111010011001010111001001101111 u
0j
0i
1n
b0 m
b1 ;
b1 C
b1000100010001010100001100100000001000000011000000110001001011010011111000110000001100000010000001111010011001010111001001101111 h
0c
0b
1g
b0 f
b1 _
b1111 A
b1111 B
1r
1p
1o
#148
b0 s
#150
0=
#155
1!
0&
0%
0[
1=
