04_SPI/spi_slave.v
`timescale 1ns/1ns
module spi_slave_bfm #(
    parameter DW = 8
)(
    input  wire          sclk,
    input  wire          ss,        
    input  wire          cpol,
    input  wire          cpha,
    input  wire          mosi,
    output wire          miso,
    input  wire [DW-1:0] tx_data,   
    output reg  [DW-1:0] rx_data,   
    output reg           rx_valid   
);

    reg [DW-1:0] tx_sh;
    reg [DW-1:0] rx_sh;
    reg [3:0]    bit_cnt;
    reg [3:0]    tcnt;    

    wire mode_xor = cpol ^ cpha;

    assign miso = tx_sh[DW-1];

    
    always @(negedge ss) begin
        tx_sh    = tx_data;
        bit_cnt  = 0;
        tcnt     = 0;
        rx_valid = 1'b0;
    end

    always @(negedge ss) rx_sh = {DW{1'b0}};

    always @(posedge sclk) if (!ss) tcnt <= tcnt + 1'b1;
    always @(negedge sclk) if (!ss) tcnt <= tcnt + 1'b1;

    
    always @(posedge sclk) begin
        if (!ss && !mode_xor) begin
            rx_sh   <= {rx_sh[DW-2:0], mosi};
            bit_cnt <= bit_cnt + 1'b1;
            if (bit_cnt == DW-1) begin
                rx_data  <= {rx_sh[DW-2:0], mosi};
                rx_valid <= 1'b1;
            end else
                rx_valid <= 1'b0;
        end
    end

    always @(negedge sclk) begin
        if (!ss && mode_xor) begin
            rx_sh   <= {rx_sh[DW-2:0], mosi};
            bit_cnt <= bit_cnt + 1'b1;
            if (bit_cnt == DW-1) begin
                rx_data  <= {rx_sh[DW-2:0], mosi};
                rx_valid <= 1'b1;
            end else
                rx_valid <= 1'b0;
        end
    end

    wire shift_now = !(cpha && tcnt == 0);
    always @(posedge sclk) if (!ss &&  mode_xor && shift_now) tx_sh <= {tx_sh[DW-2:0], 1'b0};
    always @(negedge sclk) if (!ss && !mode_xor && shift_now) tx_sh <= {tx_sh[DW-2:0], 1'b0};

endmodule

04_SPI/spi_master.v
`timescale 1ns/1ns
module spi_master #(
    parameter CLK_F        = 50_000_000,
    parameter SPI_F        = 1_000_000,
    parameter SETUP_CYCLES = 8,
    parameter HOLD_CYCLES  = 8
)(
    input  wire       clk, rst,
    input  wire       start,
    input  wire [7:0] tx_data,
    input  wire       cpol, cpha,
    input  wire       miso,
    output wire       mosi, sclk, ss,
    output reg  [7:0] rx_data,
    output wire       busy, done
);

    localparam N       = CLK_F / (2 * SPI_F);
    localparam MAX_CNT = (N > SETUP_CYCLES) ? (N > HOLD_CYCLES ? N : HOLD_CYCLES) : (SETUP_CYCLES > HOLD_CYCLES ? SETUP_CYCLES : HOLD_CYCLES);
    localparam CW      = $clog2(MAX_CNT + 1);
    localparam NE      = 16;          
    localparam EW      = $clog2(NE);

    localparam IDLE = 2'b00, SETUP = 2'b01, XFER = 2'b10, HOLD = 2'b11;

    reg [1:0]    s, ns;
    reg [2:0]    bit_cnt;
    reg [CW-1:0] cnt;
    reg [EW-1:0] ecnt;
    reg          sclk_reg, done_reg;
    reg [7:0]    tx_shift, rx_shift;

    assign done = done_reg;
    assign busy = (s == SETUP || s == XFER || s == HOLD);
    assign ss   = ~busy;
    assign sclk = sclk_reg;
    assign mosi = tx_shift[7];

    wire toggle_now   = (s == XFER) && (cnt == N - 1);
    wire rising_edge  = toggle_now && !sclk_reg;
    wire falling_edge = toggle_now &&  sclk_reg;

    wire mode_xor    = cpol ^ cpha;
    wire sample_edge = mode_xor ? falling_edge : rising_edge;
    wire shift_edge  = (mode_xor ? rising_edge : falling_edge) && !(cpha && ecnt == 0);

    wire byte_done = (s == XFER) && sample_edge && (bit_cnt == 3'd7);
    wire clk_done  = toggle_now && (ecnt == NE - 1);

    always @(*) begin
        case (s)
            IDLE : ns = start ? SETUP : IDLE;
            SETUP: ns = (cnt == SETUP_CYCLES - 1) ? XFER : SETUP;
            XFER : ns = clk_done ? HOLD : XFER;
            HOLD : ns = (cnt == HOLD_CYCLES - 1)  ? IDLE : HOLD;
            default: ns = IDLE;
        endcase
    end

    always @(posedge clk or posedge rst) begin
        if (rst) begin
            s <= IDLE; cnt <= 0; ecnt <= 0; sclk_reg <= 1'b0; done_reg <= 1'b0;
        end else begin
            s        <= ns;
            done_reg <= byte_done;

            case (s)
                IDLE : cnt <= 0;
                SETUP: cnt <= (cnt == SETUP_CYCLES - 1) ? 0 : cnt + 1'b1;
                XFER : cnt <= (cnt == N - 1)            ? 0 : cnt + 1'b1;
                HOLD : cnt <= (cnt == HOLD_CYCLES  - 1) ? 0 : cnt + 1'b1;
                default: cnt <= 0;
            endcase

            ecnt <= (s != XFER) ? 0 : (toggle_now ? ecnt + 1'b1 : ecnt);

            if (s != XFER)       sclk_reg <= cpol;
            else if (cnt == N-1) sclk_reg <= ~sclk_reg;
        end
    end

    always @(posedge clk or posedge rst) begin
        if (rst) begin
            tx_shift <= 8'd0; rx_shift <= 8'd0; bit_cnt <= 3'd0; rx_data <= 8'd0;
        end else begin
            if (start && s == IDLE) begin
                tx_shift <= tx_data;
                bit_cnt  <= 3'd0;
            end

            if (shift_edge)
                tx_shift <= {tx_shift[6:0], 1'b0};

            if (sample_edge) begin
                bit_cnt <= bit_cnt + 1'b1;
                if (bit_cnt == 3'd7) rx_data  <= {rx_shift[6:0], miso};
                else                 rx_shift <= {rx_shift[6:0], miso};
            end
        end
    end

endmodule

04_SPI/spi_tb.v
`timescale 1ns/1ns
module tb_spi_master;

    // ------------------------------------------------------------------
    // DUT configuration (kept small so the regression runs fast)
    // ------------------------------------------------------------------
    localparam CLK_F        = 50_000_000;
    localparam SPI_F        = 5_000_000;          // N = 5
    localparam SETUP_CYCLES = 4;
    localparam HOLD_CYCLES  = 6;
    localparam N            = CLK_F / (2*SPI_F);
    localparam CLK_PERIOD   = 1_000_000_000 / CLK_F; // ns
    localparam NE           = 16;                  // edges/byte

    reg clk = 0;
    always #(CLK_PERIOD/2) clk = ~clk;

    reg        rst, start, cpol, cpha;
    reg  [7:0] tx_data;
    wire       mosi, sclk, ss, busy, done;
    wire [7:0] rx_data;
    wire       miso;

    reg  [7:0] slave_tx;
    wire [7:0] slave_rx;
    wire       slave_rx_valid;

    spi_master #(
        .CLK_F(CLK_F), .SPI_F(SPI_F),
        .SETUP_CYCLES(SETUP_CYCLES), .HOLD_CYCLES(HOLD_CYCLES)
    ) dut (
        .clk(clk), .rst(rst), .start(start), .tx_data(tx_data),
        .cpol(cpol), .cpha(cpha), .miso(miso),
        .mosi(mosi), .sclk(sclk), .ss(ss),
        .rx_data(rx_data), .busy(busy), .done(done)
    );

    spi_slave_bfm #(.DW(8)) slave (
        .sclk(sclk), .ss(ss), .cpol(cpol), .cpha(cpha),
        .mosi(mosi), .miso(miso),
        .tx_data(slave_tx), .rx_data(slave_rx), .rx_valid(slave_rx_valid)
    );

    // ------------------------------------------------------------------
    // sclk edge / chip-select timestamp capture
    // ------------------------------------------------------------------
    time    edge_t [0:31];
    integer edge_n;
    time    ss_fall_t, ss_rise_t;

    always @(negedge ss) begin
        edge_n    = 0;
        ss_fall_t = $time;
    end
    always @(posedge ss) ss_rise_t = $time;
    always @(sclk) if (!ss) begin
        edge_t[edge_n] = $time;
        edge_n         = edge_n + 1;
    end

    // ------------------------------------------------------------------
    // scoreboard
    // ------------------------------------------------------------------
    integer n_checks = 0;
    integer n_fail   = 0;

    task check(input string name, input ok);
        begin
            n_checks = n_checks + 1;
            if (!ok) begin
                n_fail = n_fail + 1;
                $display("[%0t] FAIL: %s", $time, name);
            end
        end
    endtask

    // ------------------------------------------------------------------
    // transfer driver + checks
    // ------------------------------------------------------------------
    integer i;

    task do_transfer(input [7:0] m_tx, input [7:0] s_tx, input cpol_v, input cpha_v);
        begin
            wait (!busy);
            @(posedge clk); #1;
            cpol     = cpol_v;
            cpha     = cpha_v;
            tx_data  = m_tx;
            slave_tx = s_tx;
            start    = 1'b1;
            @(posedge clk); #1;
            start = 1'b0;

            @(posedge done);
            check("rx_data valid the same cycle done asserts", rx_data === s_tx);

            @(posedge ss);
            #1;
            check("slave captured exact master tx byte (full-duplex bit integrity)", slave_rx === m_tx);
            check("idle sclk returns to cpol level", sclk === cpol_v);
            check("exactly 16 sclk edges generated for one byte", edge_n == NE);

            for (i = 1; i < NE; i = i + 1)
                check("sclk half-period uniform, incl. final pulse", (edge_t[i]-edge_t[i-1]) == N*CLK_PERIOD);

            check("ss-to-first-sclk-edge setup time correct", (edge_t[0]-ss_fall_t) == (SETUP_CYCLES+N)*CLK_PERIOD);
            check("last-sclk-edge-to-ss hold time correct", (ss_rise_t-edge_t[NE-1]) == HOLD_CYCLES*CLK_PERIOD);
        end
    endtask

    // ------------------------------------------------------------------
    // stimulus
    // ------------------------------------------------------------------
    reg [7:0] pattern [0:5];
    integer   mode;
    integer   b;

    initial begin
        pattern[0] = 8'h00; pattern[1] = 8'hFF; pattern[2] = 8'hA5;
        pattern[3] = 8'h5A; pattern[4] = 8'h3C; pattern[5] = 8'h81;
    end

    initial begin
        $dumpfile("spi_tb.vcd");
        $dumpvars(0, tb_spi_master);

        rst = 1; start = 0; cpol = 0; cpha = 0; tx_data = 0; slave_tx = 0;
        repeat (5) @(posedge clk);
        rst = 0;
        repeat (3) @(posedge clk);

        // ---- directed + pseudo-random sweep across all 4 SPI modes ----
        for (mode = 0; mode < 4; mode = mode + 1) begin
            for (b = 0; b < 6; b = b + 1) begin
                $display("[%0t] starting mode=%0d cpol=%0d cpha=%0d byte=%0d", $time, mode, mode[1], mode[0], b);
                do_transfer(pattern[b], ~pattern[b] ^ 8'h3C, mode[1], mode[0]);
                $display("[%0t] finished mode=%0d byte=%0d", $time, mode, b);
                repeat (2) @(posedge clk);
            end
        end

        // ---- back-to-back: start asserted the instant IDLE is reached ----
        $display("[%0t] starting back-to-back test", $time);
        do_transfer(8'h11, 8'h22, 1'b0, 1'b0);
        $display("[%0t] back-to-back txn1 done, ss already high, issuing txn2 immediately", $time);
        tx_data  = 8'h33; slave_tx = 8'h44; cpol = 0; cpha = 0;
        start = 1'b1;
        @(posedge clk); #1;
        start = 1'b0;
        $display("[%0t] txn2 start pulsed, waiting done", $time);
        @(posedge done);
        $display("[%0t] txn2 done seen", $time);
        check("back-to-back: rx_data correct on 2nd txn", rx_data === 8'h44);
        wait (!busy); #1;
        check("back-to-back: slave saw correct 2nd byte", slave_rx === 8'h33);
        $display("[%0t] back-to-back test complete", $time);

        // ---- reset asserted mid-transfer ----
        @(posedge clk); #1;
        cpol = 0; cpha = 1; tx_data = 8'h99; slave_tx = 8'h66;
        start = 1'b1;
        @(posedge clk); #1;
        start = 1'b0;
        repeat (SETUP_CYCLES + N + 3) @(posedge clk);
        rst = 1;
        @(posedge clk); #1;
        rst = 0;
        check("reset mid-transfer: busy deasserted", busy === 1'b0);
        check("reset mid-transfer: ss deasserted",   ss   === 1'b1);
        check("reset mid-transfer: sclk at cpol",    sclk === 1'b0);
        check("reset mid-transfer: done low",        done === 1'b0);
        repeat (3) @(posedge clk);

        $display("========================================");
        $display(" SPI master regression: %0d checks, %0d failed", n_checks, n_fail);
        if (n_fail == 0) $display(" RESULT: PASS");
        else             $display(" RESULT: FAIL");
        $display("========================================");
        $finish;
    end

    // watchdog
    initial begin
        #200000;
        $display("TIMEOUT - simulation hung");
        $finish;
    end

endmodule

04_SPI/spi_tb.vcd
$date
	Sat Jun 20 13:18:41 2026
$end
$version
	Icarus Verilog
$end
$timescale
	1ns
$end
$scope module tb_spi_master $end
$var wire 1 ! ss $end
$var wire 1 " slave_rx_valid $end
$var wire 8 # slave_rx [7:0] $end
$var wire 1 $ sclk $end
$var wire 8 % rx_data [7:0] $end
$var wire 1 & mosi $end
$var wire 1 ' miso $end
$var wire 1 ( done $end
$var wire 1 ) busy $end
$var parameter 32 * CLK_F $end
$var parameter 32 + CLK_PERIOD $end
$var parameter 32 , HOLD_CYCLES $end
$var parameter 64 - N $end
$var parameter 32 . NE $end
$var parameter 32 / SETUP_CYCLES $end
$var parameter 32 0 SPI_F $end
$var reg 1 1 clk $end
$var reg 1 2 cpha $end
$var reg 1 3 cpol $end
$var reg 1 4 rst $end
$var reg 8 5 slave_tx [7:0] $end
$var reg 64 6 ss_fall_t [63:0] $end
$var reg 64 7 ss_rise_t [63:0] $end
$var reg 1 8 start $end
$var reg 8 9 tx_data [7:0] $end
$var integer 32 : b [31:0] $end
$var integer 32 ; edge_n [31:0] $end
$var integer 32 < i [31:0] $end
$var integer 32 = mode [31:0] $end
$var integer 32 > n_checks [31:0] $end
$var integer 32 ? n_fail [31:0] $end
$scope module dut $end
$var wire 1 ) busy $end
$var wire 1 @ byte_done $end
$var wire 1 1 clk $end
$var wire 1 A clk_done $end
$var wire 1 2 cpha $end
$var wire 1 3 cpol $end
$var wire 1 ( done $end
$var wire 1 B falling_edge $end
$var wire 1 C mode_xor $end
$var wire 1 D rising_edge $end
$var wire 1 4 rst $end
$var wire 1 $ sclk $end
$var wire 1 E shift_edge $end
$var wire 1 ! ss $end
$var wire 1 8 start $end
$var wire 1 F toggle_now $end
$var wire 8 G tx_data [7:0] $end
$var wire 1 H sample_edge $end
$var wire 1 & mosi $end
$var wire 1 ' miso $end
$var parameter 32 I CLK_F $end
$var parameter 32 J CW $end
$var parameter 32 K EW $end
$var parameter 2 L HOLD $end
$var parameter 32 M HOLD_CYCLES $end
$var parameter 2 N IDLE $end
$var parameter 64 O MAX_CNT $end
$var parameter 64 P N $end
$var parameter 32 Q NE $end
$var parameter 2 R SETUP $end
$var parameter 32 S SETUP_CYCLES $end
$var parameter 32 T SPI_F $end
$var parameter 2 U XFER $end
$var reg 3 V bit_cnt [2:0] $end
$var reg 3 W cnt [2:0] $end
$var reg 1 X done_reg $end
$var reg 4 Y ecnt [3:0] $end
$var reg 2 Z ns [1:0] $end
$var reg 8 [ rx_data [7:0] $end
$var reg 8 \ rx_shift [7:0] $end
$var reg 2 ] s [1:0] $end
$var reg 1 ^ sclk_reg $end
$var reg 8 _ tx_shift [7:0] $end
$upscope $end
$scope module slave $end
$var wire 1 2 cpha $end
$var wire 1 3 cpol $end
$var wire 1 ` mode_xor $end
$var wire 1 & mosi $end
$var wire 1 $ sclk $end
$var wire 1 ! ss $end
$var wire 8 a tx_data [7:0] $end
$var wire 1 b shift_now $end
$var wire 1 ' miso $end
$var parameter 32 c DW $end
$var reg 4 d bit_cnt [3:0] $end
$var reg 8 e rx_data [7:0] $end
$var reg 8 f rx_sh [7:0] $end
$var reg 1 " rx_valid $end
$var reg 4 g tcnt [3:0] $end
$var reg 8 h tx_sh [7:0] $end
$upscope $end
$scope task check $end
$var reg 1 i ok $end
$upscope $end
$scope task do_transfer $end
$var reg 1 j cpha_v $end
$var reg 1 k cpol_v $end
$var reg 8 l m_tx [7:0] $end
$var reg 8 m s_tx [7:0] $end
$upscope $end
$upscope $end
$enddefinitions $end
$comment Show the parameter values. $end
$dumpall
b1000 c
b10 U
b10011000100101101000000 T
b100 S
b1 R
b10000 Q
b101 P
b110 O
b0 N
b110 M
b11 L
b100 K
b11 J
b10111110101111000010000000 I
b10011000100101101000000 0
b100 /
b10000 .
b101 -
b110 ,
b10100 +
b10111110101111000010000000 *
$end
#0
$dumpvars
bx m
bx l
xk
xj
xi
bx h
bx g
bx f
bx e
bx d
1b
b0 a
0`
b0 _
0^
b0 ]
b0 \
b0 [
b0 Z
b0 Y
0X
b0 W
b0 V
0H
b0 G
0F
0E
0D
0C
0B
0A
0@
b0 ?
b0 >
bx =
bx <
bx ;
bx :
b0 9
08
b0 7
bx 6
b0 5
14
03
02
01
0)
0(
x'
0&
b0 %
0$
bx #
x"
1!
$end
#10
11
#20
01
#30
11
#40
01
#50
11
#60
01
#70
11
#80
01
#90
04
11
#100
01
#110
11
#120
01
#130
11
#140
01
#150
0j
0k
b11000011 m
b0 l
b0 :
b0 =
11
#160
01
#170
11
#171
b1 Z
18
b11000011 5
b11000011 a
#180
01
#190
1'
0"
b0 g
b0 d
b11000011 h
b0 f
b10111110 6
b0 ;
0!
1)
b1 ]
11
#191
08
#200
01
#210
b1 W
11
#220
01
#230
b10 W
11
#240
01
#250
b10 Z
b11 W
11
#260
01
#270
b0 W
b10 ]
11
#280
01
#290
b1 W
11
#300
01
#310
b10 W
11
#320
01
#330
b11 W
11
#340
01
#350
1H
1D
1F
b100 W
11
#360
01
#370
b1 g
b1 d
0H
0D
b1 ;
0F
b1 \
b1 V
1$
1^
b1 Y
b0 W
11
#380
01
#390
b1 W
11
#400
01
#410
b10 W
11
#420
01
#430
b11 W
11
#440
01
#450
1E
1B
1F
b100 W
11
#460
01
#470
b10000110 h
b10 g
0E
0B
b10 ;
0F
0$
0^
b10 Y
b0 W
11
#480
01
#490
b1 W
11
#500
01
#510
b10 W
11
#520
01
#530
b11 W
11
#540
01
#550
1H
1D
1F
b100 W
11
#560
01
#570
b10 d
b11 g
0H
0D
b11 ;
0F
b11 \
b10 V
1$
1^
b11 Y
b0 W
11
#580
01
#590
b1 W
11
#600
01
#610
b10 W
11
#620
01
#630
b11 W
11
#640
01
#650
1E
1B
1F
b100 W
11
#660
01
#670
0'
b100 g
b1100 h
0E
0B
b100 ;
0F
0$
0^
b100 Y
b0 W
11
#680
01
#690
b1 W
11
#700
01
#710
b10 W
11
#720
01
#730
b11 W
11
#740
01
#750
1H
1D
1F
b100 W
11
#760
01
#770
b101 g
b11 d
0H
0D
b101 ;
0F
b110 \
b11 V
1$
1^
b101 Y
b0 W
11
#780
01
#790
b1 W
11
#800
01
#810
b10 W
11
#820
01
#830
b11 W
11
#840
01
#850
1E
1B
1F
b100 W
11
#860
01
#870
b11000 h
b110 g
0E
0B
b110 ;
0F
0$
0^
b110 Y
b0 W
11
#880
01
#890
b1 W
11
#900
01
#910
b10 W
11
#920
01
#930
b11 W
11
#940
01
#950
1H
1D
1F
b100 W
11
#960
01
#970
b100 d
b111 g
0H
0D
b111 ;
0F
b1100 \
b100 V
1$
1^
b111 Y
b0 W
11
#980
01
#990
b1 W
11
#1000
01
#1010
b10 W
11
#1020
01
#1030
b11 W
11
#1040
01
#1050
1E
1B
1F
b100 W
11
#1060
01
#1070
b1000 g
b110000 h
0E
0B
b1000 ;
0F
0$
0^
b1000 Y
b0 W
11
#1080
01
#1090
b1 W
11
#1100
01
#1110
b10 W
11
#1120
01
#1130
b11 W
11
#1140
01
#1150
1H
1D
1F
b100 W
11
#1160
01
#1170
b1001 g
b101 d
0H
0D
b1001 ;
0F
b11000 \
b101 V
1$
1^
b1001 Y
b0 W
11
#1180
01
#1190
b1 W
11
#1200
01
#1210
b10 W
11
#1220
01
#1230
b11 W
11
#1240
01
#1250
1E
1B
1F
b100 W
11
#1260
01
#1270
b1100000 h
b1010 g
0E
0B
b1010 ;
0F
0$
0^
b1010 Y
b0 W
11
#1280
01
#1290
b1 W
11
#1300
01
#1310
b10 W
11
#1320
01
#1330
b11 W
11
#1340
01
#1350
1H
1D
1F
b100 W
11
#1360
01
#1370
b110 d
b1011 g
0H
0D
b1011 ;
0F
b110000 \
b110 V
1$
1^
b1011 Y
b0 W
11
#1380
01
#1390
b1 W
11
#1400
01
#1410
b10 W
11
#1420
01
#1430
b11 W
11
#1440
01
#1450
1E
1B
1F
b100 W
11
#1460
01
#1470
1'
b1100 g
b11000000 h
0E
0B
b1100 ;
0F
0$
0^
b1100 Y
b0 W
11
#1480
01
#1490
b1 W
11
#1500
01
#1510
b10 W
11
#1520
01
#1530
b11 W
11
#1540
01
#1550
1H
1D
1F
b100 W
11
#1560
01
#1570
b1101 g
b111 d
0H
0@
0D
b1101 ;
0F
b1100001 \
b111 V
1$
1^
b1101 Y
b0 W
11
#1580
01
#1590
b1 W
11
#1600
01
#1610
b10 W
11
#1620
01
#1630
b11 W
11
#1640
01
#1650
1E
1B
1F
b100 W
11
#1660
01
#1670
b10000000 h
b1110 g
0E
0B
b1110 ;
0F
0$
0^
b1110 Y
b0 W
11
#1680
01
#1690
b1 W
11
#1700
01
#1710
b10 W
11
#1720
01
#1730
b11 W
11
#1740
01
#1750
1@
1H
1D
1F
b100 W
11
#1760
01
#1770
1"
b0 #
b0 e
b1000 d
b1111 g
0H
0@
0D
b1111 ;
0F
b1 >
1i
b11000011 %
b11000011 [
b0 V
1$
1^
b1111 Y
b0 W
1(
1X
11
#1780
01
#1790
b1 W
0(
0X
11
#1800
01
#1810
b10 W
11
#1820
01
#1830
b11 W
11
#1840
01
#1850
1E
b11 Z
1B
1A
1F
b100 W
11
#1860
01
#1870
0'
b0 g
b0 h
0E
0B
b10000 ;
0A
0F
0$
0^
b0 Y
b0 W
b11 ]
11
#1880
01
#1890
b1 W
11
#1900
01
#1910
b10 W
11
#1920
01
#1930
b11 W
11
#1940
01
#1950
b100 W
11
#1960
01
#1970
b0 Z
b101 W
11
#1980
01
#1990
b11111000110 7
1!
0)
b0 W
b0 ]
11
#1991
b10000 <
b10101 >
#2000
01
#2010
11
#2020
01
#2030
b111100 m
b11111111 l
b1 :
11
#2040
01
#2050
11
#2051
b1 Z
18
b111100 5
b111100 a
b11111111 9
b11111111 G
#2060
01
#2070
b100000010110 6
b0 ;
0"
b0 d
b111100 h
0!
1)
1&
b1 ]
b11111111 _
11
#2071
08
#2080
01
#2090
b1 W
11
#2100
01
#2110
b10 W
11
#2120
01
#2130
b10 Z
b11 W
11
#2140
01
#2150
b0 W
b10 ]
11
#2160
01
#2170
b1 W
11
#2180
01
#2190
b10 W
11
#2200
01
#2210
b11 W
11
#2220
01
#2230
1H
1D
1F
b100 W
11
#2240
01
#2250
b1 g
b1 d
b1 f
0H
0D
b1 ;
0F
b11000010 \
b1 V
1$
1^
b1 Y
b0 W
11
#2260
01
#2270
b1 W
11
#2280
01
#2290
b10 W
11
#2300
01
#2310
b11 W
11
#2320
01
#2330
1E
1B
1F
b100 W
11
#2340
01
#2350
b1111000 h
b10 g
0E
0B
b10 ;
0F
0$
0^
b10 Y
b0 W
b11111110 _
11
#2360
01
#2370
b1 W
11
#2380
01
#2390
b10 W
11
#2400
01
#2410
b11 W
11
#2420
01
#2430
1H
1D
1F
b100 W
11
#2440
01
#2450
b10 d
b11 f
b11 g
0H
0D
b11 ;
0F
b10000100 \
b10 V
1$
1^
b11 Y
b0 W
11
#2460
01
#2470
b1 W
11
#2480
01
#2490
b10 W
11
#2500
01
#2510
b11 W
11
#2520
01
#2530
1E
1B
1F
b100 W
11
#2540
01
#2550
1'
b100 g
b11110000 h
0E
0B
b100 ;
0F
0$
0^
b100 Y
b0 W
b11111100 _
11
#2560
01
#2570
b1 W
11
#2580
01
#2590
b10 W
11
#2600
01
#2610
b11 W
11
#2620
01
#2630
1H
1D
1F
b100 W
11
#2640
01
#2650
b101 g
b11 d
b111 f
0H
0D
b101 ;
0F
b1001 \
b11 V
1$
1^
b101 Y
b0 W
11
#2660
01
#2670
b1 W
11
#2680
01
#2690
b10 W
11
#2700
01
#2710
b11 W
11
#2720
01
#2730
1E
1B
1F
b100 W
11
#2740
01
#2750
b11100000 h
b110 g
0E
0B
b110 ;
0F
0$
0^
b110 Y
b0 W
b11111000 _
11
#2760
01
#2770
b1 W
11
#2780
01
#2790
b10 W
11
#2800
01
#2810
b11 W
11
#2820
01
#2830
1H
1D
1F
b100 W
11
#2840
01
#2850
b100 d
b1111 f
b111 g
0H
0D
b111 ;
0F
b10011 \
b100 V
1$
1^
b111 Y
b0 W
11
#2860
01
#2870
b1 W
11
#2880
01
#2890
b10 W
11
#2900
01
#2910
b11 W
11
#2920
01
#2930
1E
1B
1F
b100 W
11
#2940
01
#2950
b1000 g
b11000000 h
0E
0B
b1000 ;
0F
0$
0^
b1000 Y
b0 W
b11110000 _
11
#2960
01
#2970
b1 W
11
#2980
01
#2990
b10 W
11
#3000
01
#3010
b11 W
11
#3020
01
#3030
1H
1D
1F
b100 W
11
#3040
01
#3050
b1001 g
b101 d
b11111 f
0H
0D
b1001 ;
0F
b100111 \
b101 V
1$
1^
b1001 Y
b0 W
11
#3060
01
#3070
b1 W
11
#3080
01
#3090
b10 W
11
#3100
01
#3110
b11 W
11
#3120
01
#3130
1E
1B
1F
b100 W
11
#3140
01
#3150
b10000000 h
b1010 g
0E
0B
b1010 ;
0F
0$
0^
b1010 Y
b0 W
b11100000 _
11
#3160
01
#3170
b1 W
11
#3180
01
#3190
b10 W
11
#3200
01
#3210
b11 W
11
#3220
01
#3230
1H
1D
1F
b100 W
11
#3240
01
#3250
b110 d
b111111 f
b1011 g
0H
0D
b1011 ;
0F
b1001111 \
b110 V
1$
1^
b1011 Y
b0 W
11
#3260
01
#3270
b1 W
11
#3280
01
#3290
b10 W
11
#3300
01
#3310
b11 W
11
#3320
01
#3330
1E
1B
1F
b100 W
11
#3340
01
#3350
0'
b1100 g
b0 h
0E
0B
b1100 ;
0F
0$
0^
b1100 Y
b0 W
b11000000 _
11
#3360
01
#3370
b1 W
11
#3380
01
#3390
b10 W
11
#3400
01
#3410
b11 W
11
#3420
01
#3430
1H
1D
1F
b100 W
11
#3440
01
#3450
b1101 g
b111 d
b1111111 f
0H
0@
0D
b1101 ;
0F
b10011110 \
b111 V
1$
1^
b1101 Y
b0 W
11
#3460
01
#3470
b1 W
11
#3480
01
#3490
b10 W
11
#3500
01
#3510
b11 W
11
#3520
01
#3530
1E
1B
1F
b100 W
11
#3540
01
#3550
b1110 g
0E
0B
b1110 ;
0F
0$
0^
b1110 Y
b0 W
b10000000 _
11
#3560
01
#3570
b1 W
11
#3580
01
#3590
b10 W
11
#3600
01
#3610
b11 W
11
#3620
01
#3630
1@
1H
1D
1F
b100 W
11
#3640
01
#3650
1"
b11111111 #
b11111111 e
b1000 d
b11111111 f
b1111 g
0H
0@
0D
b1111 ;
0F
b10110 >
b111100 %
b111100 [
b0 V
1$
1^
b1111 Y
b0 W
1(
1X
11
#3660
01
#3670
b1 W
0(
0X
11
#3680
01
#3690
b10 W
11
#3700
01
#3710
b11 W
11
#3720
01
#3730
1E
b11 Z
1B
1A
1F
b100 W
11
#3740
01
#3750
b0 g
0E
0B
b10000 ;
0A
0F
0&
0$
0^
b0 Y
b0 W
b11 ]
b0 _
11
#3760
01
#3770
b1 W
11
#3780
01
#3790
b10 W
11
#3800
01
#3810
b11 W
11
#3820
01
#3830
b100 W
11
#3840
01
#3850
b0 Z
b101 W
11
#3860
01
#3870
b111100011110 7
1!
0)
b0 W
b0 ]
11
#3871
b10000 <
b101010 >
#3880
01
#3890
11
#3900
01
#3910
b1100110 m
b10100101 l
b10 :
11
#3920
01
#3930
11
#3931
b1 Z
18
b1100110 5
b1100110 a
b10100101 9
b10100101 G
#3940
01
#3950
0"
b0 d
b1100110 h
b0 f
b111101101110 6
b0 ;
0!
1)
1&
b1 ]
b10100101 _
11
#3951
08
#3960
01
#3970
b1 W
11
#3980
01
#3990
b10 W
11
#4000
01
#4010
b10 Z
b11 W
11
#4020
01
#4030
b0 W
b10 ]
11
#4040
01
#4050
b1 W
11
#4060
01
#4070
b10 W
11
#4080
01
#4090
b11 W
11
#4100
01
#4110
1H
1D
1F
b100 W
11
#4120
01
#4130
b1 g
b1 d
b1 f
0H
0D
b1 ;
0F
b111100 \
b1 V
1$
1^
b1 Y
b0 W
11
#4140
01
#4150
b1 W
11
#4160
01
#4170
b10 W
11
#4180
01
#4190
b11 W
11
#4200
01
#4210
1E
1B
1F
b100 W
11
#4220
01
#4230
1'
b11001100 h
b10 g
0E
0B
b10 ;
0F
0&
0$
0^
b10 Y
b0 W
b1001010 _
11
#4240
01
#4250
b1 W
11
#4260
01
#4270
b10 W
11
#4280
01
#4290
b11 W
11
#4300
01
#4310
1H
1D
1F
b100 W
11
#4320
01
#4330
b10 d
b10 f
b11 g
0H
0D
b11 ;
0F
b1111001 \
b10 V
1$
1^
b11 Y
b0 W
11
#4340
01
#4350
b1 W
11
#4360
01
#4370
b10 W
11
#4380
01
#4390
b11 W
11
#4400
01
#4410
1E
1B
1F
b100 W
11
#4420
01
#4430
b100 g
b10011000 h
0E
0B
b100 ;
0F
1&
0$
0^
b100 Y
b0 W
b10010100 _
11
#4440
01
#4450
b1 W
11
#4460
01
#4470
b10 W
11
#4480
01
#4490
b11 W
11
#4500
01
#4510
1H
1D
1F
b100 W
11
#4520
01
#4530
b101 g
b11 d
b101 f
0H
0D
b101 ;
0F
b11110011 \
b11 V
1$
1^
b101 Y
b0 W
11
#4540
01
#4550
b1 W
11
#4560
01
#4570
b10 W
11
#4580
01
#4590
b11 W
11
#4600
01
#4610
1E
1B
1F
b100 W
11
#4620
01
#4630
0'
b110000 h
b110 g
0E
0B
b110 ;
0F
0&
0$
0^
b110 Y
b0 W
b101000 _
11
#4640
01
#4650
b1 W
11
#4660
01
#4670
b10 W
11
#4680
01
#4690
b11 W
11
#4700
01
#4710
1H
1D
1F
b100 W
11
#4720
01
#4730
b100 d
b1010 f
b111 g
0H
0D
b111 ;
0F
b11100110 \
b100 V
1$
1^
b111 Y
b0 W
11
#4740
01
#4750
b1 W
11
#4760
01
#4770
b10 W
11
#4780
01
#4790
b11 W
11
#4800
01
#4810
1E
1B
1F
b100 W
11
#4820
01
#4830
b1000 g
b1100000 h
0E
0B
b1000 ;
0F
0$
0^
b1000 Y
b0 W
b1010000 _
11
#4840
01
#4850
b1 W
11
#4860
01
#4870
b10 W
11
#4880
01
#4890
b11 W
11
#4900
01
#4910
1H
1D
1F
b100 W
11
#4920
01
#4930
b1001 g
b101 d
b10100 f
0H
0D
b1001 ;
0F
b11001100 \
b101 V
1$
1^
b1001 Y
b0 W
11
#4940
01
#4950
b1 W
11
#4960
01
#4970
b10 W
11
#4980
01
#4990
b11 W
11
#5000
01
#5010
1E
1B
1F
b100 W
11
#5020
01
#5030
1'
b11000000 h
b1010 g
0E
0B
b1010 ;
0F
1&
0$
0^
b1010 Y
b0 W
b10100000 _
11
#5040
01
#5050
b1 W
11
#5060
01
#5070
b10 W
11
#5080
01
